{
  "1.jpg": "Trao đổi với Tuổi Trẻ sáng 16 - 11, chủ tịch UBND tỉnh",
  "2.jpg": "Nguyễn Xuân Phúc cho biết ngay sau khi thảm nạn xảy ra",
  "3.jpg": "làm thiệt mạng 19 công nhân đào đãi vàng của Công ty TNHH",
  "4.jpg": "Trường Sơn, tỉnh đã chỉ đạo các ngành chức năng của tỉnh",
  "5.jpg": "tập trung khắc phục hậu quả, tìm kiếm những người bị mất",
  "6.jpg": "tích trong lũ quét, đồng thời quyết định trích từ ngân sách tỉnh",
  "7.jpg": "hỗ trợ mỗi nạn nhân thiệt mạng 1 triệu đồng và 500.000 ngàn",
  "8.jpg": "đồng đối với những người bị thương.",
  "9.jpg": "Ngoài ra Công ty TNHH Trường Sơn quyết định hỗ trợ gia đình 19 nạn nhân",
  "10.jpg": "thiệt mạng trong đợt lũ quét vừa qua, mỗi gia đình 50 triệu đồng để lo chi phí",
  "11.jpg": "mai táng. Ở Bệnh viện huyện Phước Sơn, bốn con người được xem là lớn số, là",
  "12.jpg": "may mắn cũng đang chịu đựng đau thương không ít. Tôi đến khi các y sĩ ở",
  "13.jpg": "đây vừa làm thuốc buổi chiều cho họ. Bị trầy sướt và sưng tấy người, một ngón",
  "14.jpg": "tay bị gẫy, Nguyễn Hoài Nam (23 tuổi) vẫn quên đau, ứa nước mắt khóc cho",
  "15.jpg": "người bạn Bùi Văn Luyến cùng xóm với mình : \" Nó hay nói đùa.",
  "16.jpg": "Xem tivi về, thấy trời mưa lớn nó nằm nói với em : \" Làm nghề này dễ bị sập",
  "17.jpg": "hầm, mưa lũ làm núi lở sập trại lắm. Trong anh em mình tau mà chết thì tội",
  "18.jpg": "nghiệp mẹ tau lắm! \". Nó nói chưa đầy hai phút thì nghe ầm ầm... \". Phạm Văn",
  "19.jpg": "Hiếu (19 tuổi) bị gẫy một xương sườn, rách tai, sưng bầm khắp người, cũng",
  "20.jpg": "cố nói lên nỗi đau của mình với bạn bè xấu số, nhất là với Luyến :",
  "21.jpg": "\" Nó không cha, 18 tuổi đã cố cùng mẹ làm được mái nhà hai gian.",
  "22.jpg": "Thấy mẹ che dụm bên góc hè nấu ăn khổ cực, nó nói cuối năm lĩnh",
  "23.jpg": "tiền về làm cho mẹ cái bếp nhỏ. Vậy mà... \". Mừng mình còn sống, họ",
  "24.jpg": "lại thương kẻ ra đi. \" Biết làm vàng ở rừng sâu là cực. Nhưng vì cuộc",
  "25.jpg": "sống khó khăn nên mới ra đi. Ai cũng mong đến tết để nhận lương dồn",
  "26.jpg": "một lần mang về. Ai ngờ... \" - Lê Đức Hà (18 tuổi) nói bên giường bệnh",
  "27.jpg": "như một lời than thở... Bãi đào vàng Phước Thành vẫn còn là nơi bỏ",
  "28.jpg": "ngỏ bởi cho đến giờ chưa có ai vào đó, kể cả các cán bộ chức năng.",
  "29.jpg": "Nhưng rồi những người đào vàng cũng sẽ vào. Khi đã đưa hết người nằm",
  "30.jpg": "xuống về quê, họ phải quay lại với hầm vàng. Nhìn những khuôn mặt rất",
  "31.jpg": "trẻ của họ, nghĩ đến những bất trắc vốn chứa đầy nơi các hầm đào",
  "32.jpg": "vàng giữa thăm thẳm Trường Sơn, nhớ lại những cái chết của 49 người",
  "33.jpg": "đào vàng cũng vì lũ làm lở núi vùi lấp trại hồi năm 1997 ở bãi vàng",
  "34.jpg": "Phước Chánh (kề Phước Thành)... tôi không khỏi chạnh lòng.",
  "35.jpg": "\" Nghề nông ở quê mình khổ quá. Dẫu sao tụi em cũng phải",
  "36.jpg": "cố vì mỗi tháng kiếm được năm sáu trăm ngàn cũng quí lắm... \",",
  "37.jpg": "lời của \" cậu bé \" Chu Văn Minh, 18 tuổi, chưa một lần cắp",
  "38.jpg": "sách đi học, đã khiến tôi không còn biết nói gì thêm..."
}